fraud_analysis/VERSION
fraud_analysis/__init__.py
fraud_analysis/config.yml
fraud_analysis/evaluate.py
fraud_analysis/pipeline.py
fraud_analysis/predict.py
fraud_analysis/train.py
fraud_analysis/config/__init__.py
fraud_analysis/config/core.py
fraud_analysis/datasets/raw/creditcard.csv
fraud_analysis/datasets/test/X_test.csv
fraud_analysis/datasets/test/y_test.csv
fraud_analysis/outputs/saved_col_names.pkl
fraud_analysis/processing/__init__.py
fraud_analysis/processing/data_manager.py
fraud_analysis/processing/features.py
fraud_analysis/trained_models/__init__.py
fraud_analysis/trained_models/fraud_pipeline_v0.0.4.pkl
tid_credit_card_fraud_prediction-0.0.4.dist-info/LICENSE
tid_credit_card_fraud_prediction-0.0.4.dist-info/METADATA
tid_credit_card_fraud_prediction-0.0.4.dist-info/WHEEL
tid_credit_card_fraud_prediction-0.0.4.dist-info/top_level.txt
tid_credit_card_fraud_prediction-0.0.4.dist-info/RECORD
