Metadata-Version: 2.1
Name: tid-credit-card-fraud-prediction
Version: 0.0.4
Summary: Train a Random Forest model to predict credit card fraudulent transactions
Home-page: https://github.com/hfung4/credit_card_fraud_detection/tree/main/credit_card_fraud_production
Author: HenryF
Author-email: henryhfung21@gmail.com
License: BSD-3
Classifier: License :: OSI Approved :: MIT License
Classifier: Programming Language :: Python
Classifier: Programming Language :: Python :: 3
Classifier: Programming Language :: Python :: 3.6
Classifier: Programming Language :: Python :: 3.7
Classifier: Programming Language :: Python :: 3.8
Classifier: Programming Language :: Python :: 3.9
Classifier: Programming Language :: Python :: 3.10
Classifier: Programming Language :: Python :: Implementation :: CPython
Classifier: Programming Language :: Python :: Implementation :: PyPy
Requires-Python: >=3.10.0
License-File: LICENSE
Requires-Dist: anyio (==3.6.2)
Requires-Dist: appnope (==0.1.3)
Requires-Dist: argon2-cffi (==21.3.0)
Requires-Dist: argon2-cffi-bindings (==21.2.0)
Requires-Dist: arrow (==1.2.3)
Requires-Dist: asttokens (==2.2.1)
Requires-Dist: attrs (==22.2.0)
Requires-Dist: autoviz (==0.1.58)
Requires-Dist: backcall (==0.2.0)
Requires-Dist: beautifulsoup4 (==4.11.1)
Requires-Dist: black (==22.12.0)
Requires-Dist: bleach (==5.0.1)
Requires-Dist: bokeh (==2.4.3)
Requires-Dist: cachetools (==5.3.0)
Requires-Dist: category-encoders (==2.6.0)
Requires-Dist: certifi (==2022.12.7)
Requires-Dist: cffi (==1.15.1)
Requires-Dist: chardet (==5.1.0)
Requires-Dist: charset-normalizer (==3.0.1)
Requires-Dist: click (==8.1.3)
Requires-Dist: cloudpickle (==2.2.0)
Requires-Dist: colorama (==0.4.6)
Requires-Dist: colorcet (==3.0.1)
Requires-Dist: comm (==0.1.2)
Requires-Dist: contourpy (==1.0.7)
Requires-Dist: cycler (==0.11.0)
Requires-Dist: dask (==2023.1.0)
Requires-Dist: debugpy (==1.6.5)
Requires-Dist: decorator (==5.1.1)
Requires-Dist: defusedxml (==0.7.1)
Requires-Dist: distlib (==0.3.6)
Requires-Dist: distributed (==2023.1.0)
Requires-Dist: emoji (==2.2.0)
Requires-Dist: entrypoints (==0.4)
Requires-Dist: exceptiongroup (==1.1.0)
Requires-Dist: executing (==1.2.0)
Requires-Dist: fastjsonschema (==2.16.2)
Requires-Dist: feather-format (==0.4.1)
Requires-Dist: feature-engine (==1.5.2)
Requires-Dist: featurewiz (==0.2.4)
Requires-Dist: filelock (==3.9.0)
Requires-Dist: fonttools (==4.38.0)
Requires-Dist: fqdn (==1.5.1)
Requires-Dist: fsspec (==2022.11.0)
Requires-Dist: HeapDict (==1.0.1)
Requires-Dist: holoviews (==1.14.9)
Requires-Dist: hvplot (==0.8.2)
Requires-Dist: idna (==3.4)
Requires-Dist: imbalanced-learn (==0.10.1)
Requires-Dist: imblearn (==0.0)
Requires-Dist: iniconfig (==2.0.0)
Requires-Dist: ipykernel (==6.20.1)
Requires-Dist: ipython (==8.8.0)
Requires-Dist: ipython-genutils (==0.2.0)
Requires-Dist: ipywidgets (==8.0.4)
Requires-Dist: isoduration (==20.11.0)
Requires-Dist: jedi (==0.18.2)
Requires-Dist: Jinja2 (==3.1.2)
Requires-Dist: joblib (==1.2.0)
Requires-Dist: jsonpointer (==2.3)
Requires-Dist: jsonschema (==4.17.3)
Requires-Dist: jupyter (==1.0.0)
Requires-Dist: jupyter-console (==6.4.4)
Requires-Dist: jupyter-events (==0.6.3)
Requires-Dist: jupyter-client (==7.4.9)
Requires-Dist: jupyter-core (==5.1.3)
Requires-Dist: jupyter-server (==2.1.0)
Requires-Dist: jupyter-server-terminals (==0.4.4)
Requires-Dist: jupyterlab-pygments (==0.2.2)
Requires-Dist: jupyterlab-widgets (==3.0.5)
Requires-Dist: kiwisolver (==1.4.4)
Requires-Dist: lightgbm (==3.3.4)
Requires-Dist: locket (==1.0.0)
Requires-Dist: Markdown (==3.4.1)
Requires-Dist: MarkupSafe (==2.1.1)
Requires-Dist: matplotlib (==3.6.3)
Requires-Dist: matplotlib-inline (==0.1.6)
Requires-Dist: mistune (==2.0.4)
Requires-Dist: msgpack (==1.0.4)
Requires-Dist: mypy-extensions (==0.4.3)
Requires-Dist: nbclassic (==0.4.8)
Requires-Dist: nbclient (==0.7.2)
Requires-Dist: nbconvert (==7.2.7)
Requires-Dist: nbformat (==5.7.3)
Requires-Dist: nest-asyncio (==1.5.6)
Requires-Dist: networkx (==3.0)
Requires-Dist: nltk (==3.8.1)
Requires-Dist: notebook (==6.5.2)
Requires-Dist: notebook-shim (==0.2.2)
Requires-Dist: numpy (==1.24.1)
Requires-Dist: packaging (==23.0)
Requires-Dist: pandas (==1.5.2)
Requires-Dist: pandocfilters (==1.5.0)
Requires-Dist: panel (==0.12.7)
Requires-Dist: param (==1.12.3)
Requires-Dist: parso (==0.8.3)
Requires-Dist: partd (==1.3.0)
Requires-Dist: pathspec (==0.10.3)
Requires-Dist: patsy (==0.5.3)
Requires-Dist: pexpect (==4.8.0)
Requires-Dist: pickleshare (==0.7.5)
Requires-Dist: Pillow (==9.4.0)
Requires-Dist: platformdirs (==2.6.2)
Requires-Dist: plotly (==5.12.0)
Requires-Dist: pluggy (==1.0.0)
Requires-Dist: prometheus-client (==0.15.0)
Requires-Dist: prompt-toolkit (==3.0.36)
Requires-Dist: psutil (==5.9.4)
Requires-Dist: ptyprocess (==0.7.0)
Requires-Dist: pure-eval (==0.2.2)
Requires-Dist: pyamg (==4.2.3)
Requires-Dist: pyarrow (==7.0.0)
Requires-Dist: pycparser (==2.21)
Requires-Dist: pyct (==0.4.8)
Requires-Dist: pydantic (==1.10.4)
Requires-Dist: Pygments (==2.14.0)
Requires-Dist: pyparsing (==3.0.9)
Requires-Dist: pyproject-api (==1.5.0)
Requires-Dist: pyrsistent (==0.19.3)
Requires-Dist: pytest (==7.2.1)
Requires-Dist: python-dateutil (==2.8.2)
Requires-Dist: python-json-logger (==2.0.4)
Requires-Dist: pytz (==2022.7.1)
Requires-Dist: pyviz-comms (==2.2.1)
Requires-Dist: PyYAML (==6.0)
Requires-Dist: pyzmq (==25.0.0)
Requires-Dist: qtconsole (==5.4.0)
Requires-Dist: QtPy (==2.3.0)
Requires-Dist: regex (==2022.10.31)
Requires-Dist: requests (==2.28.2)
Requires-Dist: rfc3339-validator (==0.1.4)
Requires-Dist: rfc3986-validator (==0.1.1)
Requires-Dist: scikit-learn (==1.2.0)
Requires-Dist: scipy (==1.10.0)
Requires-Dist: seaborn (==0.12.2)
Requires-Dist: Send2Trash (==1.8.0)
Requires-Dist: six (==1.16.0)
Requires-Dist: sniffio (==1.3.0)
Requires-Dist: sortedcontainers (==2.4.0)
Requires-Dist: soupsieve (==2.3.2.post1)
Requires-Dist: stack-data (==0.6.2)
Requires-Dist: statsmodels (==0.13.5)
Requires-Dist: strictyaml (==1.6.2)
Requires-Dist: tblib (==1.7.0)
Requires-Dist: tenacity (==8.1.0)
Requires-Dist: terminado (==0.17.1)
Requires-Dist: textblob (==0.17.1)
Requires-Dist: threadpoolctl (==3.1.0)
Requires-Dist: tinycss2 (==1.2.1)
Requires-Dist: tomli (==2.0.1)
Requires-Dist: toolz (==0.12.0)
Requires-Dist: tornado (==6.2)
Requires-Dist: tox (==4.3.5)
Requires-Dist: tqdm (==4.64.1)
Requires-Dist: traitlets (==5.8.1)
Requires-Dist: typing-extensions (==4.4.0)
Requires-Dist: uri-template (==1.2.0)
Requires-Dist: urllib3 (==1.26.14)
Requires-Dist: virtualenv (==20.17.1)
Requires-Dist: wcwidth (==0.2.6)
Requires-Dist: webcolors (==1.12)
Requires-Dist: webencodings (==0.5.1)
Requires-Dist: websocket-client (==1.4.2)
Requires-Dist: widgetsnbextension (==4.0.5)
Requires-Dist: wordcloud (==1.8.2.2)
Requires-Dist: xgboost (==1.7.3)
Requires-Dist: xlrd (==2.0.1)
Requires-Dist: zict (==2.2.0)
